smart_vector/__init__.py
smart_vector/smart_vector.py
smart_vector-1.1.4.dist-info/METADATA
smart_vector-1.1.4.dist-info/WHEEL
smart_vector-1.1.4.dist-info/top_level.txt
smart_vector-1.1.4.dist-info/RECORD
