Metadata-Version: 2.1
Name: smart-vector
Version: 1.1.4
Summary: smart vector db
Author-email: John Yan <yanxiaohua@smartchart.cn>
Classifier: Programming Language :: Python :: 3
Classifier: License :: OSI Approved :: Apache Software License
Classifier: Operating System :: OS Independent
Requires-Python: >=3.7
Requires-Dist: smartchart
